analytics_tasks/__init__.py
analytics_tasks/automate_office/__init__.py
analytics_tasks/automate_office/build_batch.py
analytics_tasks/automate_office/build_explore.py
analytics_tasks/automate_office/input/____control.xlsm
analytics_tasks/automate_office/input/data/event_1/xy_hr_bar.csv
analytics_tasks/automate_office/input/data/event_1/xyv_multiline.csv
analytics_tasks/automate_office/input/data/event_1/xyv_stacked_bar.csv
analytics_tasks/automate_office/input/data/event_1/xyz_hr_bar_k.csv
analytics_tasks/automate_office/input/img/flag_india.png
analytics_tasks/automate_office/input/img/event_1/1.png
analytics_tasks/automate_office/input/img/event_1/32_6.png
analytics_tasks/automate_office/input/img/event_1/33_6.png
analytics_tasks/automate_office/input/img/event_1/39_7.png
analytics_tasks/automate_office/input/img/event_1/dog.png
analytics_tasks/automate_office/input/img/event_1/flow_alluvial_py_r_sql_big_input_png.png
analytics_tasks/file_search/__init__.py
analytics_tasks/file_search/build.py
analytics_tasks/file_search/functions.py
analytics_tasks/file_search/load_search_polars.py
analytics_tasks/ml/__init__.py
analytics_tasks/ml/functions/__init__.py
analytics_tasks/ml/functions/info_schema_parser.py
analytics_tasks/ml/text/__init__.py
analytics_tasks/ml/text/info_schema_parser/__init__.py
analytics_tasks/utils/__init__.py
analytics_tasks/utils/fakedatagenerator.py
analytics_tasks/utils/functions.py
analytics_tasks/visual_library/__init__.py
analytics_tasks/visual_library/build.py
analytics_tasks/visual_library/visual_library_demo.py
analytics_tasks/visual_library/visual_library_demo_old.py
analytics_tasks/visual_library/gallery/____settings/colors.xlsm
analytics_tasks/visual_library/gallery/change/xyv_multiline.bas
analytics_tasks/visual_library/gallery/change/xyv_multiline.csv
analytics_tasks/visual_library/gallery/change/xyv_multiline.jpg
analytics_tasks/visual_library/gallery/change/xyv_multiline.png
analytics_tasks-0.1.0.dist-info/licenses/LICENSE.md
analytics_tasks-0.1.0.dist-info/METADATA
analytics_tasks-0.1.0.dist-info/WHEEL
analytics_tasks-0.1.0.dist-info/top_level.txt
analytics_tasks-0.1.0.dist-info/RECORD
